SimpleMDDataCatalog/__init__.py
SimpleMDDataCatalog/analysis_functions.py
SimpleMDDataCatalog/dcat_model.py
SimpleMDDataCatalog/generate_catalog.py
SimpleMDDataCatalog/import_catalog.py
SimpleMDDataCatalog/spreadsheet_to_ld.py
SimpleMDDataCatalog/uri_handling.py
simplemddatacatalog-0.1.13.dist-info/METADATA
simplemddatacatalog-0.1.13.dist-info/WHEEL
simplemddatacatalog-0.1.13.dist-info/licenses/LICENSE
simplemddatacatalog-0.1.13.dist-info/RECORD
