Metadata-Version: 2.4
Name: SimpleMDDataCatalog
Version: 0.1.13
Summary: A simple package that supports data catalogging in a spreadsheet and publishes the data catalog as markdown on git(hub)
Project-URL: Homepage, https://github.com/uuidea/SimpleMDDataCatalog
Project-URL: Issues, https://github.com/uuidea/SimpleMDDataCatalog/issues
Author-email: Joep van Genuchten <joep@uuidea.eu>
License-File: LICENSE
Classifier: License :: OSI Approved :: Apache Software License
Classifier: Operating System :: OS Independent
Classifier: Programming Language :: Python :: 3
Requires-Python: >=3.8
Requires-Dist: igraph
Requires-Dist: matplotlib
Requires-Dist: openpyxl
Requires-Dist: pandas
Requires-Dist: rdflib
Requires-Dist: validators
Requires-Dist: wordcloud
